<?xml version="1.0" standalone="yes"?>
<Simulation_Log>
  <Simulation>
    <Simulation_Name>20181109_mountalex_evac_ffdi100a</Simulation_Name>
    <Start_Time>2017-02-16T13:00:00+11:00</Start_Time>
    <End_Time>2017-02-16T23:00:00+11:00</End_Time>
    <Area_Burnt>19200.695288085946</Area_Burnt>
    <Criticality_Score>317.96820000000008</Criticality_Score>
    <Max_McArthurs_Spotting_Distance>9774.5582610117563</Max_McArthurs_Spotting_Distance>
  </Simulation>
  <Progress>
    <Hour>1.6666666666666667E-05</Hour>
    <Area_Burnt>0</Area_Burnt>
    <Fire_Count>1</Fire_Count>
    <Convective_Output>0</Convective_Output>
  </Progress>
  <Progress>
    <Hour>0.025840833333333334</Hour>
    <Area_Burnt>1.416015625E-06</Area_Burnt>
    <Fire_Count>1</Fire_Count>
    <Convective_Output>0</Convective_Output>
  </Progress>
  <Progress>
    <Hour>0.053104166666666668</Hour>
    <Area_Burnt>0.00023564453125</Area_Burnt>
    <Fire_Count>1</Fire_Count>
    <Convective_Output>0</Convective_Output>
  </Progress>
  <Progress>
    <Hour>0.0836225</Hour>
    <Area_Burnt>0.00349345703125</Area_Burnt>
    <Fire_Count>1</Fire_Count>
    <Convective_Output>0</Convective_Output>
  </Progress>
  <Progress>
    <Hour>0.12173222222222221</Hour>
    <Area_Burnt>0.032951708984375</Area_Burnt>
    <Fire_Count>1</Fire_Count>
    <Convective_Output>0</Convective_Output>
  </Progress>
  <Progress>
    <Hour>0.17655638888888889</Hour>
    <Area_Burnt>0.33441552734375</Area_Burnt>
    <Fire_Count>1</Fire_Count>
    <Convective_Output>0</Convective_Output>
  </Progress>
  <Progress>
    <Hour>0.2555175</Hour>
    <Area_Burnt>1.19156943359375</Area_Burnt>
    <Fire_Count>1</Fire_Count>
    <Convective_Output>0</Convective_Output>
  </Progress>
  <Progress>
    <Hour>0.58885083333333332</Hour>
    <Area_Burnt>10.05202412109375</Area_Burnt>
    <Fire_Count>1</Fire_Count>
    <Convective_Output>2887</Convective_Output>
    <A_1>1.9998</A_1>
  </Progress>
  <Progress>
    <Hour>0.92218416666666658</Hour>
    <Area_Burnt>30.516965478515626</Area_Burnt>
    <Fire_Count>4</Fire_Count>
    <Convective_Output>51283</Convective_Output>
    <A_1>1.9998</A_1>
  </Progress>
  <Progress>
    <Hour>1</Hour>
    <Area_Burnt>38.044695068359381</Area_Burnt>
    <Fire_Count>7</Fire_Count>
    <Convective_Output>24566</Convective_Output>
    <A_1>1.9998</A_1>
  </Progress>
  <Progress>
    <Hour>1.1885122222222222</Hour>
    <Area_Burnt>59.6345705078125</Area_Burnt>
    <Fire_Count>12</Fire_Count>
    <Convective_Output>22135</Convective_Output>
    <A_1>14.998500000000002</A_1>
  </Progress>
  <Progress>
    <Hour>1.3344869444444445</Hour>
    <Area_Burnt>86.571913134765651</Area_Burnt>
    <Fire_Count>10</Fire_Count>
    <Convective_Output>24816</Convective_Output>
    <A_1>22.997700000000002</A_1>
  </Progress>
  <Progress>
    <Hour>1.4767872222222223</Hour>
    <Area_Burnt>137.37387944335939</Area_Burnt>
    <Fire_Count>6</Fire_Count>
    <Convective_Output>48641</Convective_Output>
    <A_1>38.996099999999991</A_1>
  </Progress>
  <Progress>
    <Hour>1.6199216666666667</Hour>
    <Area_Burnt>190.2273563476563</Area_Burnt>
    <Fire_Count>12</Fire_Count>
    <Convective_Output>38722</Convective_Output>
    <A_1>62.993699999999961</A_1>
  </Progress>
  <Progress>
    <Hour>1.7631902777777777</Hour>
    <Area_Burnt>272.83292080078121</Area_Burnt>
    <Fire_Count>8</Fire_Count>
    <Convective_Output>42674</Convective_Output>
    <A_1>63.993599999999958</A_1>
  </Progress>
  <Progress>
    <Hour>1.8962811111111111</Hour>
    <Area_Burnt>374.56187973632819</Area_Burnt>
    <Fire_Count>13</Fire_Count>
    <Convective_Output>28766</Convective_Output>
    <A_1>87.991199999999921</A_1>
  </Progress>
  <Progress>
    <Hour>2</Hour>
    <Area_Burnt>466.8232674804687</Area_Burnt>
    <Fire_Count>9</Fire_Count>
    <Convective_Output>43774</Convective_Output>
    <A_1>91.990799999999908</A_1>
  </Progress>
  <Progress>
    <Hour>2.1774305555555555</Hour>
    <Area_Burnt>610.01536328124973</Area_Burnt>
    <Fire_Count>108</Fire_Count>
    <Convective_Output>80351</Convective_Output>
    <A_1>96.990299999999891</A_1>
  </Progress>
  <Progress>
    <Hour>2.3215327777777777</Hour>
    <Area_Burnt>937.62451874999977</Area_Burnt>
    <Fire_Count>58</Fire_Count>
    <Convective_Output>185340</Convective_Output>
    <A_1>97.990199999999888</A_1>
  </Progress>
  <Progress>
    <Hour>2.5682863888888887</Hour>
    <Area_Burnt>1341.4841359863281</Area_Burnt>
    <Fire_Count>29</Fire_Count>
    <Convective_Output>176770</Convective_Output>
    <A_1>101.98979999999987</A_1>
  </Progress>
  <Progress>
    <Hour>2.6810655555555556</Hour>
    <Area_Burnt>1552.2280211914062</Area_Burnt>
    <Fire_Count>103</Fire_Count>
    <Convective_Output>77974</Convective_Output>
    <A_1>103.98959999999988</A_1>
  </Progress>
  <Progress>
    <Hour>2.7912766666666666</Hour>
    <Area_Burnt>1794.7525715332015</Area_Burnt>
    <Fire_Count>193</Fire_Count>
    <Convective_Output>187251</Convective_Output>
    <A_1>109.98899999999986</A_1>
  </Progress>
  <Progress>
    <Hour>2.9103027777777775</Hour>
    <Area_Burnt>2238.3245788085937</Area_Burnt>
    <Fire_Count>201</Fire_Count>
    <Convective_Output>248827</Convective_Output>
    <A_1>146.98529999999977</A_1>
  </Progress>
  <Progress>
    <Hour>3</Hour>
    <Area_Burnt>2685.8242178222613</Area_Burnt>
    <Fire_Count>125</Fire_Count>
    <Convective_Output>195862</Convective_Output>
    <A_1>150.98489999999973</A_1>
  </Progress>
  <Progress>
    <Hour>3.1120341666666667</Hour>
    <Area_Burnt>3206.5842756347652</Area_Burnt>
    <Fire_Count>78</Fire_Count>
    <Convective_Output>258519</Convective_Output>
    <A_1>150.98489999999973</A_1>
  </Progress>
  <Progress>
    <Hour>3.2471674999999998</Hour>
    <Area_Burnt>3850.6109100585923</Area_Burnt>
    <Fire_Count>47</Fire_Count>
    <Convective_Output>109525</Convective_Output>
    <A_1>161.98379999999969</A_1>
  </Progress>
  <Progress>
    <Hour>3.3610680555555552</Hour>
    <Area_Burnt>4205.2697003417961</Area_Burnt>
    <Fire_Count>41</Fire_Count>
    <Convective_Output>108909</Convective_Output>
    <A_1>164.98349999999968</A_1>
  </Progress>
  <Progress>
    <Hour>3.4763297222222223</Hour>
    <Area_Burnt>4644.9078336914081</Area_Burnt>
    <Fire_Count>46</Fire_Count>
    <Convective_Output>74024</Convective_Output>
    <A_1>185.98139999999961</A_1>
  </Progress>
  <Progress>
    <Hour>3.5572769444444443</Hour>
    <Area_Burnt>4960.8386225097665</Area_Burnt>
    <Fire_Count>41</Fire_Count>
    <Convective_Output>106312</Convective_Output>
    <A_1>197.98019999999957</A_1>
  </Progress>
  <Progress>
    <Hour>3.6376405555555555</Hour>
    <Area_Burnt>5299.7397685546839</Area_Burnt>
    <Fire_Count>40</Fire_Count>
    <Convective_Output>97850</Convective_Output>
    <A_1>204.97949999999955</A_1>
  </Progress>
  <Progress>
    <Hour>3.7177491666666667</Hour>
    <Area_Burnt>5618.3908944824207</Area_Burnt>
    <Fire_Count>42</Fire_Count>
    <Convective_Output>83955</Convective_Output>
    <A_1>214.97849999999951</A_1>
  </Progress>
  <Progress>
    <Hour>3.7971947222222222</Hour>
    <Area_Burnt>5931.7616972656233</Area_Burnt>
    <Fire_Count>30</Fire_Count>
    <Convective_Output>68341</Convective_Output>
    <A_1>227.9771999999995</A_1>
  </Progress>
  <Progress>
    <Hour>3.8763552777777774</Hour>
    <Area_Burnt>6255.0734109375</Area_Burnt>
    <Fire_Count>40</Fire_Count>
    <Convective_Output>70772</Convective_Output>
    <A_1>232.97669999999948</A_1>
  </Progress>
  <Progress>
    <Hour>3.9552430555555556</Hour>
    <Area_Burnt>6617.2708641601548</Area_Burnt>
    <Fire_Count>36</Fire_Count>
    <Convective_Output>133206</Convective_Output>
    <A_1>238.97609999999946</A_1>
  </Progress>
  <Progress>
    <Hour>4</Hour>
    <Area_Burnt>6878.7608704101576</Area_Burnt>
    <Fire_Count>30</Fire_Count>
    <Convective_Output>89620</Convective_Output>
    <A_1>250.97489999999942</A_1>
  </Progress>
  <Progress>
    <Hour>4.13609</Hour>
    <Area_Burnt>7537.02116713867</Area_Burnt>
    <Fire_Count>24</Fire_Count>
    <Convective_Output>75049</Convective_Output>
    <A_1>252.97469999999942</A_1>
  </Progress>
  <Progress>
    <Hour>4.2259488888888885</Hour>
    <Area_Burnt>7886.0105256835941</Area_Burnt>
    <Fire_Count>20</Fire_Count>
    <Convective_Output>50095</Convective_Output>
    <A_1>260.97389999999945</A_1>
  </Progress>
  <Progress>
    <Hour>4.3535611111111105</Hour>
    <Area_Burnt>8328.9345879394568</Area_Burnt>
    <Fire_Count>14</Fire_Count>
    <Convective_Output>67332</Convective_Output>
    <A_1>266.97329999999954</A_1>
  </Progress>
  <Progress>
    <Hour>4.5072719444444447</Hour>
    <Area_Burnt>8791.4691171875056</Area_Burnt>
    <Fire_Count>9</Fire_Count>
    <Convective_Output>57757</Convective_Output>
    <A_1>270.97289999999958</A_1>
  </Progress>
  <Progress>
    <Hour>4.635563888888889</Hour>
    <Area_Burnt>9162.912228173831</Area_Burnt>
    <Fire_Count>5</Fire_Count>
    <Convective_Output>47376</Convective_Output>
    <A_1>272.97269999999958</A_1>
  </Progress>
  <Progress>
    <Hour>4.79083</Hour>
    <Area_Burnt>9568.6541186035229</Area_Burnt>
    <Fire_Count>8</Fire_Count>
    <Convective_Output>35284</Convective_Output>
    <A_1>291.97079999999977</A_1>
  </Progress>
  <Progress>
    <Hour>4.9435755555555554</Hour>
    <Area_Burnt>10014.278340478522</Area_Burnt>
    <Fire_Count>7</Fire_Count>
    <Convective_Output>46299</Convective_Output>
    <A_1>293.97059999999976</A_1>
  </Progress>
  <Progress>
    <Hour>5</Hour>
    <Area_Burnt>10195.19502641602</Area_Burnt>
    <Fire_Count>8</Fire_Count>
    <Convective_Output>41069</Convective_Output>
    <A_1>293.97059999999976</A_1>
  </Progress>
  <Progress>
    <Hour>5.138975277777778</Hour>
    <Area_Burnt>10986.89244648438</Area_Burnt>
    <Fire_Count>5</Fire_Count>
    <Convective_Output>39274</Convective_Output>
    <A_1>294.97049999999979</A_1>
  </Progress>
  <Progress>
    <Hour>5.3327658333333332</Hour>
    <Area_Burnt>12482.43019174805</Area_Burnt>
    <Fire_Count>3</Fire_Count>
    <Convective_Output>19245</Convective_Output>
    <A_1>298.97009999999983</A_1>
  </Progress>
  <Progress>
    <Hour>5.4769047222222218</Hour>
    <Area_Burnt>13027.14458793946</Area_Burnt>
    <Fire_Count>3</Fire_Count>
    <Convective_Output>36653</Convective_Output>
    <A_1>299.96999999999986</A_1>
  </Progress>
  <Progress>
    <Hour>5.6522572222222216</Hour>
    <Area_Burnt>13400.626947265629</Area_Burnt>
    <Fire_Count>4</Fire_Count>
    <Convective_Output>44691</Convective_Output>
    <A_1>299.96999999999986</A_1>
  </Progress>
  <Progress>
    <Hour>5.8003141666666664</Hour>
    <Area_Burnt>13700.486597412113</Area_Burnt>
    <Fire_Count>11</Fire_Count>
    <Convective_Output>39528</Convective_Output>
    <A_1>299.96999999999986</A_1>
  </Progress>
  <Progress>
    <Hour>5.9805908333333333</Hour>
    <Area_Burnt>14065.228899560552</Area_Burnt>
    <Fire_Count>13</Fire_Count>
    <Convective_Output>63858</Convective_Output>
    <A_1>302.96969999999982</A_1>
  </Progress>
  <Progress>
    <Hour>6</Hour>
    <Area_Burnt>14109.17027148438</Area_Burnt>
    <Fire_Count>12</Fire_Count>
    <Convective_Output>48840</Convective_Output>
    <A_1>302.96969999999982</A_1>
  </Progress>
  <Progress>
    <Hour>6.1607552777777776</Hour>
    <Area_Burnt>14454.453240820316</Area_Burnt>
    <Fire_Count>41</Fire_Count>
    <Convective_Output>40203</Convective_Output>
    <A_1>303.96959999999984</A_1>
  </Progress>
  <Progress>
    <Hour>6.3068088888888889</Hour>
    <Area_Burnt>14763.596463232432</Area_Burnt>
    <Fire_Count>37</Fire_Count>
    <Convective_Output>43146</Convective_Output>
    <A_1>305.96939999999984</A_1>
  </Progress>
  <Progress>
    <Hour>6.4888397222222221</Hour>
    <Area_Burnt>15175.611773144537</Area_Burnt>
    <Fire_Count>15</Fire_Count>
    <Convective_Output>42074</Convective_Output>
    <A_1>316.96830000000011</A_1>
  </Progress>
  <Progress>
    <Hour>6.6941322222222217</Hour>
    <Area_Burnt>15633.597339306645</Area_Burnt>
    <Fire_Count>11</Fire_Count>
    <Convective_Output>53534</Convective_Output>
    <A_1>316.96830000000011</A_1>
  </Progress>
  <Progress>
    <Hour>6.9012777777777776</Hour>
    <Area_Burnt>16062.518945751957</Area_Burnt>
    <Fire_Count>7</Fire_Count>
    <Convective_Output>40061</Convective_Output>
    <A_1>316.96830000000011</A_1>
  </Progress>
  <Progress>
    <Hour>7</Hour>
    <Area_Burnt>16253.110068994147</Area_Burnt>
    <Fire_Count>5</Fire_Count>
    <Convective_Output>16646</Convective_Output>
    <A_1>316.96830000000011</A_1>
  </Progress>
  <Progress>
    <Hour>7.2448108333333332</Hour>
    <Area_Burnt>16665.740602880869</Area_Burnt>
    <Fire_Count>1</Fire_Count>
    <Convective_Output>16509</Convective_Output>
    <A_1>316.96830000000011</A_1>
  </Progress>
  <Progress>
    <Hour>7.4367211111111109</Hour>
    <Area_Burnt>16943.199948437508</Area_Burnt>
    <Fire_Count>2</Fire_Count>
    <Convective_Output>16886</Convective_Output>
    <A_1>316.96830000000011</A_1>
  </Progress>
  <Progress>
    <Hour>7.623787222222222</Hour>
    <Area_Burnt>17207.159110205088</Area_Burnt>
    <Fire_Count>2</Fire_Count>
    <Convective_Output>21848</Convective_Output>
    <A_1>316.96830000000011</A_1>
  </Progress>
  <Progress>
    <Hour>7.8342030555555553</Hour>
    <Area_Burnt>17600.324051220708</Area_Burnt>
    <Fire_Count>2</Fire_Count>
    <Convective_Output>17015</Convective_Output>
    <A_1>316.96830000000011</A_1>
  </Progress>
  <Progress>
    <Hour>8</Hour>
    <Area_Burnt>17788.179219384776</Area_Burnt>
    <Fire_Count>2</Fire_Count>
    <Convective_Output>14370</Convective_Output>
    <A_1>316.96830000000011</A_1>
  </Progress>
  <Progress>
    <Hour>8.22974111111111</Hour>
    <Area_Burnt>18056.72124501954</Area_Burnt>
    <Fire_Count>1</Fire_Count>
    <Convective_Output>19037</Convective_Output>
    <A_1>316.96830000000011</A_1>
  </Progress>
  <Progress>
    <Hour>8.4085158333333325</Hour>
    <Area_Burnt>18246.980388037118</Area_Burnt>
    <Fire_Count>1</Fire_Count>
    <Convective_Output>12358</Convective_Output>
    <A_1>316.96830000000011</A_1>
  </Progress>
  <Progress>
    <Hour>8.7418491666666664</Hour>
    <Area_Burnt>18525.134029199227</Area_Burnt>
    <Fire_Count>1</Fire_Count>
    <Convective_Output>14457</Convective_Output>
    <A_1>317.96820000000008</A_1>
  </Progress>
  <Progress>
    <Hour>9</Hour>
    <Area_Burnt>18710.078100634775</Area_Burnt>
    <Fire_Count>1</Fire_Count>
    <Convective_Output>9520</Convective_Output>
    <A_1>317.96820000000008</A_1>
  </Progress>
  <Progress>
    <Hour>9.3333333333333321</Hour>
    <Area_Burnt>18908.727620849619</Area_Burnt>
    <Fire_Count>1</Fire_Count>
    <Convective_Output>10800</Convective_Output>
    <A_1>317.96820000000008</A_1>
  </Progress>
  <Progress>
    <Hour>9.66370611111111</Hour>
    <Area_Burnt>19053.118504248054</Area_Burnt>
    <Fire_Count>1</Fire_Count>
    <Convective_Output>6423</Convective_Output>
    <A_1>317.96820000000008</A_1>
  </Progress>
  <Progress>
    <Hour>9.9970394444444448</Hour>
    <Area_Burnt>19199.293016455085</Area_Burnt>
    <Fire_Count>1</Fire_Count>
    <Convective_Output>6664</Convective_Output>
    <A_1>317.96820000000008</A_1>
  </Progress>
  <Progress>
    <Hour>10</Hour>
    <Area_Burnt>19200.695288085946</Area_Burnt>
    <Fire_Count>1</Fire_Count>
    <Convective_Output>1898</Convective_Output>
    <A_1>317.96820000000008</A_1>
  </Progress>
  <Fuel>
    <Fuel_Type>3020</Fuel_Type>
    <Desc>Temperate Grassland / Sedgeland </Desc>
    <Percentage>53.031923018176265</Percentage>
    <Area_Ha>10182.497944132336</Area_Ha>
  </Fuel>
  <Fuel>
    <Fuel_Type>3006</Fuel_Type>
    <Desc>Forest with shrub</Desc>
    <Percentage>30.410875210019856</Percentage>
    <Area_Ha>5839.099483515979</Area_Ha>
  </Fuel>
  <Fuel>
    <Fuel_Type>3009</Fuel_Type>
    <Desc>Woodland Grass/Herb-rich</Desc>
    <Percentage>8.721551855811823</Percentage>
    <Area_Ha>1674.598596226833</Area_Ha>
  </Fuel>
  <Fuel>
    <Fuel_Type>3047</Fuel_Type>
    <Desc>Non-Combustible</Desc>
    <Percentage>2.47441576294486</Percentage>
    <Area_Ha>475.1050308034097</Area_Ha>
  </Fuel>
  <Fuel>
    <Fuel_Type>3000</Fuel_Type>
    <Desc>Water, sand, no vegetation</Desc>
    <Percentage>2.1383839926683978</Percentage>
    <Area_Ha>410.58459452146519</Area_Ha>
  </Fuel>
  <Fuel>
    <Fuel_Type>3007</Fuel_Type>
    <Desc>Forest herb-rich</Desc>
    <Percentage>1.4663204521154727</Percentage>
    <Area_Ha>281.54372195757611</Area_Ha>
  </Fuel>
  <Fuel>
    <Fuel_Type>3046</Fuel_Type>
    <Desc>Eaten Out Grass</Desc>
    <Percentage>0.672063540552925</Percentage>
    <Area_Ha>129.04087256388905</Area_Ha>
  </Fuel>
  <Fuel>
    <Fuel_Type>3014</Fuel_Type>
    <Desc>Riparian shrubland</Desc>
    <Percentage>0.53459599816709946</Percentage>
    <Area_Ha>102.6461486303663</Area_Ha>
  </Fuel>
  <Fuel>
    <Fuel_Type>3098</Fuel_Type>
    <Desc>Softwood Plantation</Desc>
    <Percentage>0.25966091339544828</Percentage>
    <Area_Ha>49.856700763320774</Area_Ha>
  </Fuel>
  <Fuel>
    <Fuel_Type>3008</Fuel_Type>
    <Desc>Dry Open Forest shrub/herbs</Desc>
    <Percentage>0.19856422789063694</Percentage>
    <Area_Ha>38.125712348421771</Area_Ha>
  </Fuel>
  <Fuel>
    <Fuel_Type>3029</Fuel_Type>
    <Desc>Ephemeral grass/sedge/herbs</Desc>
    <Percentage>0.045822514128608521</Percentage>
    <Area_Ha>8.7982413111742535</Area_Ha>
  </Fuel>
  <Fuel>
    <Fuel_Type>3097</Fuel_Type>
    <Desc>Orchard / Vineyard</Desc>
    <Percentage>0.045822514128608521</Percentage>
    <Area_Ha>8.7982413111742535</Area_Ha>
  </Fuel>
  <Weather>
    <Weather_Time>2017-02-16T11:00:00+11:00</Weather_Time>
    <Temperature>37</Temperature>
    <Rel_Humidity>15</Rel_Humidity>
    <Wind_Speed>40</Wind_Speed>
    <Wind_Direction>360</Wind_Direction>
    <Percent_Curing>100</Percent_Curing>
    <Drought_Factor>10</Drought_Factor>
    <Cloud_Cover>0</Cloud_Cover>
  </Weather>
  <Weather>
    <Weather_Time>2017-02-16T12:00:00+11:00</Weather_Time>
    <Temperature>40</Temperature>
    <Rel_Humidity>13</Rel_Humidity>
    <Wind_Speed>42</Wind_Speed>
    <Wind_Direction>360</Wind_Direction>
    <Percent_Curing>100</Percent_Curing>
    <Drought_Factor>10</Drought_Factor>
    <Cloud_Cover>0</Cloud_Cover>
  </Weather>
  <Weather>
    <Weather_Time>2017-02-16T13:00:00+11:00</Weather_Time>
    <Temperature>41</Temperature>
    <Rel_Humidity>11</Rel_Humidity>
    <Wind_Speed>45</Wind_Speed>
    <Wind_Direction>350</Wind_Direction>
    <Percent_Curing>100</Percent_Curing>
    <Drought_Factor>10</Drought_Factor>
    <Cloud_Cover>0</Cloud_Cover>
  </Weather>
  <Weather>
    <Weather_Time>2017-02-16T13:30:00+11:00</Weather_Time>
    <Temperature>41</Temperature>
    <Rel_Humidity>11</Rel_Humidity>
    <Wind_Speed>46</Wind_Speed>
    <Wind_Direction>350</Wind_Direction>
    <Percent_Curing>100</Percent_Curing>
    <Drought_Factor>10</Drought_Factor>
    <Cloud_Cover>0</Cloud_Cover>
  </Weather>
  <Weather>
    <Weather_Time>2017-02-16T14:00:00+11:00</Weather_Time>
    <Temperature>41</Temperature>
    <Rel_Humidity>11</Rel_Humidity>
    <Wind_Speed>46</Wind_Speed>
    <Wind_Direction>350</Wind_Direction>
    <Percent_Curing>100</Percent_Curing>
    <Drought_Factor>10</Drought_Factor>
    <Cloud_Cover>0</Cloud_Cover>
  </Weather>
  <Weather>
    <Weather_Time>2017-02-16T15:00:00+11:00</Weather_Time>
    <Temperature>40</Temperature>
    <Rel_Humidity>11</Rel_Humidity>
    <Wind_Speed>45</Wind_Speed>
    <Wind_Direction>350</Wind_Direction>
    <Percent_Curing>100</Percent_Curing>
    <Drought_Factor>10</Drought_Factor>
    <Cloud_Cover>0</Cloud_Cover>
  </Weather>
  <Weather>
    <Weather_Time>2017-02-16T16:00:00+11:00</Weather_Time>
    <Temperature>39</Temperature>
    <Rel_Humidity>12</Rel_Humidity>
    <Wind_Speed>44</Wind_Speed>
    <Wind_Direction>340</Wind_Direction>
    <Percent_Curing>100</Percent_Curing>
    <Drought_Factor>10</Drought_Factor>
    <Cloud_Cover>0</Cloud_Cover>
  </Weather>
  <Weather>
    <Weather_Time>2017-02-16T17:00:00+11:00</Weather_Time>
    <Temperature>39</Temperature>
    <Rel_Humidity>12</Rel_Humidity>
    <Wind_Speed>44</Wind_Speed>
    <Wind_Direction>330</Wind_Direction>
    <Percent_Curing>100</Percent_Curing>
    <Drought_Factor>10</Drought_Factor>
    <Cloud_Cover>0</Cloud_Cover>
  </Weather>
  <Weather>
    <Weather_Time>2017-02-16T18:00:00+11:00</Weather_Time>
    <Temperature>38</Temperature>
    <Rel_Humidity>13</Rel_Humidity>
    <Wind_Speed>43</Wind_Speed>
    <Wind_Direction>330</Wind_Direction>
    <Percent_Curing>100</Percent_Curing>
    <Drought_Factor>10</Drought_Factor>
    <Cloud_Cover>0</Cloud_Cover>
  </Weather>
  <Weather>
    <Weather_Time>2017-02-16T18:15:00+11:00</Weather_Time>
    <Temperature>35</Temperature>
    <Rel_Humidity>23</Rel_Humidity>
    <Wind_Speed>50</Wind_Speed>
    <Wind_Direction>220</Wind_Direction>
    <Percent_Curing>100</Percent_Curing>
    <Drought_Factor>10</Drought_Factor>
    <Cloud_Cover>0</Cloud_Cover>
  </Weather>
  <Weather>
    <Weather_Time>2017-02-16T18:45:00+11:00</Weather_Time>
    <Temperature>33</Temperature>
    <Rel_Humidity>26</Rel_Humidity>
    <Wind_Speed>44</Wind_Speed>
    <Wind_Direction>220</Wind_Direction>
    <Percent_Curing>100</Percent_Curing>
    <Drought_Factor>10</Drought_Factor>
    <Cloud_Cover>0</Cloud_Cover>
  </Weather>
  <Weather>
    <Weather_Time>2017-02-16T20:00:00+11:00</Weather_Time>
    <Temperature>32</Temperature>
    <Rel_Humidity>29</Rel_Humidity>
    <Wind_Speed>38</Wind_Speed>
    <Wind_Direction>200</Wind_Direction>
    <Percent_Curing>100</Percent_Curing>
    <Drought_Factor>10</Drought_Factor>
    <Cloud_Cover>0</Cloud_Cover>
  </Weather>
  <Weather>
    <Weather_Time>2017-02-16T21:00:00+11:00</Weather_Time>
    <Temperature>31</Temperature>
    <Rel_Humidity>31</Rel_Humidity>
    <Wind_Speed>34</Wind_Speed>
    <Wind_Direction>200</Wind_Direction>
    <Percent_Curing>100</Percent_Curing>
    <Drought_Factor>10</Drought_Factor>
    <Cloud_Cover>0</Cloud_Cover>
  </Weather>
  <Weather>
    <Weather_Time>2017-02-16T22:00:00+11:00</Weather_Time>
    <Temperature>29</Temperature>
    <Rel_Humidity>34</Rel_Humidity>
    <Wind_Speed>28</Wind_Speed>
    <Wind_Direction>200</Wind_Direction>
    <Percent_Curing>100</Percent_Curing>
    <Drought_Factor>10</Drought_Factor>
    <Cloud_Cover>0</Cloud_Cover>
  </Weather>
  <Weather>
    <Weather_Time>2017-02-16T23:00:00+11:00</Weather_Time>
    <Temperature>28</Temperature>
    <Rel_Humidity>36</Rel_Humidity>
    <Wind_Speed>26</Wind_Speed>
    <Wind_Direction>210</Wind_Direction>
    <Percent_Curing>100</Percent_Curing>
    <Drought_Factor>10</Drought_Factor>
    <Cloud_Cover>0</Cloud_Cover>
  </Weather>
</Simulation_Log>